<?xml version="1.0" encoding="UTF-8"?>
<sbml xmlns="http://www.sbml.org/sbml/level2" xmlns:html="http://www.w3.org/1999/xhtml" xmlns:jigcell="http://www.sbml.org/2001/ns/jigcell" xmlns:math="http://www.w3.org/1998/Math/MathML" xmlns:rdf="http://www.w3.org/1999/02/22-rdf-syntax-ns#" xmlns:sbml="http://www.sbml.org/sbml/level2" xmlns:xlink="http://www.w3.org/1999/xlink" level="2" version="1">
  <model name="Example_1">
<notes><p xmlns="http://www.w3.org/1999/xhtml"></p></notes>
    <listOfCompartments>
      <compartment id="cell" name="cell" size="1.0" />
    </listOfCompartments>
    <listOfSpecies>
      <species id="G4" name="G4" compartment="cell" />
      <species id="G3" name="G3" compartment="cell" />
      <species id="G14" name="G14" compartment="cell" />
      <species id="G13" name="G13" compartment="cell" />
      <species id="G1" name="G1" compartment="cell" />
      <species id="G12" name="G12" compartment="cell" />
      <species id="G0" name="G0" compartment="cell" />
      <species id="G11" name="G11" compartment="cell" />
      <species id="G10" name="G10" compartment="cell" />
      <species id="G8" name="G8" compartment="cell" />
      <species id="G7" name="G7" compartment="cell" />
      <species id="G6" name="G6" compartment="cell" />
      <species id="G5" name="G5" compartment="cell" />
      <species id="_void_" name="_void_" compartment="cell" initialAmount="0.0" boundaryCondition="true" constant="true" />
    </listOfSpecies>
    <listOfReactions>
      <reaction id="G4_synthesis" name="G4_synthesis: ~(1*2)" reversible="false">
        <listOfReactants>
          <speciesReference species="_void_" />
        </listOfReactants>
        <listOfProducts>
          <speciesReference species="G4" />
        </listOfProducts>
        <listOfModifiers>
          <modifierSpeciesReference species="G0" />
          <modifierSpeciesReference species="G8" />
        </listOfModifiers>
        <kineticLaw>
          <listOfParameters>
            <parameter id="max" name="max" value="0.016888359785378962" />
            <parameter id="deltaProtein" name="deltaProtein" value="0.016162649236063576" />
            <parameter id="maxTranslation" name="maxTranslation" value="0.016162649236063576" />
            <parameter id="bindsAsComplex_1" name="bindsAsComplex_1" value="1.0" />
            <parameter id="numActivators_1" name="numActivators_1" value="2.0" />
            <parameter id="numDeactivators_1" name="numDeactivators_1" value="0.0" />
            <parameter id="a_0" name="a_0" value="1.0" />
            <parameter id="a_1" name="a_1" value="0.084718087045633" />
            <parameter id="k_1" name="k_1" value="0.2932716452656314" />
            <parameter id="k_2" name="k_2" value="0.37153114878106863" />
            <parameter id="n_1" name="n_1" value="5.055137441402445" />
            <parameter id="n_2" name="n_2" value="3.909319280467572" />
          </listOfParameters>
        </kineticLaw>
      </reaction>
      <reaction id="G4_degradation" name="G4_degradation" reversible="false">
        <listOfReactants>
          <speciesReference species="G4" />
        </listOfReactants>
        <listOfProducts>
          <speciesReference species="_void_" />
        </listOfProducts>
        <kineticLaw>
          <listOfParameters>
            <parameter id="delta" name="delta" value="0.016888359785378962" />
          </listOfParameters>
        </kineticLaw>
      </reaction>
      <reaction id="G3_synthesis" name="G3_synthesis: (1~2)" reversible="false">
        <listOfReactants>
          <speciesReference species="_void_" />
        </listOfReactants>
        <listOfProducts>
          <speciesReference species="G3" />
        </listOfProducts>
        <listOfModifiers>
          <modifierSpeciesReference species="G1" />
          <modifierSpeciesReference species="G0" />
        </listOfModifiers>
        <kineticLaw>
          <listOfParameters>
            <parameter id="max" name="max" value="0.018294944072282132" />
            <parameter id="deltaProtein" name="deltaProtein" value="0.06836329459094086" />
            <parameter id="maxTranslation" name="maxTranslation" value="0.06836329459094086" />
            <parameter id="bindsAsComplex_1" name="bindsAsComplex_1" value="1.0" />
            <parameter id="numActivators_1" name="numActivators_1" value="1.0" />
            <parameter id="numDeactivators_1" name="numDeactivators_1" value="1.0" />
            <parameter id="a_0" name="a_0" value="0.03086573356793423" />
            <parameter id="a_1" name="a_1" value="1.0" />
            <parameter id="k_1" name="k_1" value="0.5831293130293489" />
            <parameter id="k_2" name="k_2" value="0.37465192407369613" />
            <parameter id="n_1" name="n_1" value="2.4832787010488366" />
            <parameter id="n_2" name="n_2" value="2.560236730674787" />
          </listOfParameters>
        </kineticLaw>
      </reaction>
      <reaction id="G3_degradation" name="G3_degradation" reversible="false">
        <listOfReactants>
          <speciesReference species="G3" />
        </listOfReactants>
        <listOfProducts>
          <speciesReference species="_void_" />
        </listOfProducts>
        <kineticLaw>
          <listOfParameters>
            <parameter id="delta" name="delta" value="0.018294944072282132" />
          </listOfParameters>
        </kineticLaw>
      </reaction>
      <reaction id="G14_synthesis" name="G14_synthesis: ~(1*2)" reversible="false">
        <listOfReactants>
          <speciesReference species="_void_" />
        </listOfReactants>
        <listOfProducts>
          <speciesReference species="G14" />
        </listOfProducts>
        <listOfModifiers>
          <modifierSpeciesReference species="G12" />
          <modifierSpeciesReference species="G0" />
        </listOfModifiers>
        <kineticLaw>
          <listOfParameters>
            <parameter id="max" name="max" value="0.09010947939479574" />
            <parameter id="deltaProtein" name="deltaProtein" value="0.020970431719035683" />
            <parameter id="maxTranslation" name="maxTranslation" value="0.020970431719035683" />
            <parameter id="bindsAsComplex_1" name="bindsAsComplex_1" value="1.0" />
            <parameter id="numActivators_1" name="numActivators_1" value="2.0" />
            <parameter id="numDeactivators_1" name="numDeactivators_1" value="0.0" />
            <parameter id="a_0" name="a_0" value="1.0" />
            <parameter id="a_1" name="a_1" value="0.10411717954550115" />
            <parameter id="k_1" name="k_1" value="0.13422570081194862" />
            <parameter id="k_2" name="k_2" value="0.6010816740803421" />
            <parameter id="n_1" name="n_1" value="4.112598890118026" />
            <parameter id="n_2" name="n_2" value="3.517584854864216" />
          </listOfParameters>
        </kineticLaw>
      </reaction>
      <reaction id="G14_degradation" name="G14_degradation" reversible="false">
        <listOfReactants>
          <speciesReference species="G14" />
        </listOfReactants>
        <listOfProducts>
          <speciesReference species="_void_" />
        </listOfProducts>
        <kineticLaw>
          <listOfParameters>
            <parameter id="delta" name="delta" value="0.09010947939479574" />
          </listOfParameters>
        </kineticLaw>
      </reaction>
      <reaction id="G13_synthesis" name="G13_synthesis: ~(1~2) + ~(3)" reversible="false">
        <listOfReactants>
          <speciesReference species="_void_" />
        </listOfReactants>
        <listOfProducts>
          <speciesReference species="G13" />
        </listOfProducts>
        <listOfModifiers>
          <modifierSpeciesReference species="G14" />
          <modifierSpeciesReference species="G0" />
          <modifierSpeciesReference species="G12" />
        </listOfModifiers>
        <kineticLaw>
          <listOfParameters>
            <parameter id="max" name="max" value="0.021547549515325098" />
            <parameter id="deltaProtein" name="deltaProtein" value="0.030531068245256532" />
            <parameter id="maxTranslation" name="maxTranslation" value="0.030531068245256532" />
            <parameter id="bindsAsComplex_1" name="bindsAsComplex_1" value="1.0" />
            <parameter id="numActivators_1" name="numActivators_1" value="1.0" />
            <parameter id="numDeactivators_1" name="numDeactivators_1" value="1.0" />
            <parameter id="bindsAsComplex_2" name="bindsAsComplex_2" value="0.0" />
            <parameter id="numActivators_2" name="numActivators_2" value="1.0" />
            <parameter id="numDeactivators_2" name="numDeactivators_2" value="0.0" />
            <parameter id="a_0" name="a_0" value="1.0" />
            <parameter id="a_1" name="a_1" value="0.5357200343124477" />
            <parameter id="a_2" name="a_2" value="0.5074511896061674" />
            <parameter id="a_3" name="a_3" value="0.043171223918615165" />
            <parameter id="k_1" name="k_1" value="0.9123230782430619" />
            <parameter id="k_2" name="k_2" value="0.7241927285166457" />
            <parameter id="k_3" name="k_3" value="0.7943007038137876" />
            <parameter id="n_1" name="n_1" value="2.128528020110131" />
            <parameter id="n_2" name="n_2" value="2.7197880942501054" />
            <parameter id="n_3" name="n_3" value="6.216111029880593" />
          </listOfParameters>
        </kineticLaw>
      </reaction>
      <reaction id="G13_degradation" name="G13_degradation" reversible="false">
        <listOfReactants>
          <speciesReference species="G13" />
        </listOfReactants>
        <listOfProducts>
          <speciesReference species="_void_" />
        </listOfProducts>
        <kineticLaw>
          <listOfParameters>
            <parameter id="delta" name="delta" value="0.021547549515325098" />
          </listOfParameters>
        </kineticLaw>
      </reaction>
      <reaction id="G1_synthesis" name="G1_synthesis: ~(1)" reversible="false">
        <listOfReactants>
          <speciesReference species="_void_" />
        </listOfReactants>
        <listOfProducts>
          <speciesReference species="G1" />
        </listOfProducts>
        <listOfModifiers>
          <modifierSpeciesReference species="G0" />
        </listOfModifiers>
        <kineticLaw>
          <listOfParameters>
            <parameter id="max" name="max" value="0.022219923554389915" />
            <parameter id="deltaProtein" name="deltaProtein" value="0.02663242326732702" />
            <parameter id="maxTranslation" name="maxTranslation" value="0.02663242326732702" />
            <parameter id="bindsAsComplex_1" name="bindsAsComplex_1" value="0.0" />
            <parameter id="numActivators_1" name="numActivators_1" value="1.0" />
            <parameter id="numDeactivators_1" name="numDeactivators_1" value="0.0" />
            <parameter id="a_0" name="a_0" value="1.0" />
            <parameter id="a_1" name="a_1" value="0.0996329176661167" />
            <parameter id="k_1" name="k_1" value="0.48650451458990573" />
            <parameter id="n_1" name="n_1" value="5.632509099470276" />
          </listOfParameters>
        </kineticLaw>
      </reaction>
      <reaction id="G1_degradation" name="G1_degradation" reversible="false">
        <listOfReactants>
          <speciesReference species="G1" />
        </listOfReactants>
        <listOfProducts>
          <speciesReference species="_void_" />
        </listOfProducts>
        <kineticLaw>
          <listOfParameters>
            <parameter id="delta" name="delta" value="0.022219923554389915" />
          </listOfParameters>
        </kineticLaw>
      </reaction>
      <reaction id="G12_synthesis" name="G12_synthesis: (1) + ~(2)" reversible="false">
        <listOfReactants>
          <speciesReference species="_void_" />
        </listOfReactants>
        <listOfProducts>
          <speciesReference species="G12" />
        </listOfProducts>
        <listOfModifiers>
          <modifierSpeciesReference species="G0" />
          <modifierSpeciesReference species="G4" />
        </listOfModifiers>
        <kineticLaw>
          <listOfParameters>
            <parameter id="max" name="max" value="0.01960647439081646" />
            <parameter id="deltaProtein" name="deltaProtein" value="0.029863185201547387" />
            <parameter id="maxTranslation" name="maxTranslation" value="0.029863185201547387" />
            <parameter id="bindsAsComplex_1" name="bindsAsComplex_1" value="1.0" />
            <parameter id="numActivators_1" name="numActivators_1" value="1.0" />
            <parameter id="numDeactivators_1" name="numDeactivators_1" value="0.0" />
            <parameter id="bindsAsComplex_2" name="bindsAsComplex_2" value="1.0" />
            <parameter id="numActivators_2" name="numActivators_2" value="1.0" />
            <parameter id="numDeactivators_2" name="numDeactivators_2" value="0.0" />
            <parameter id="a_0" name="a_0" value="0.4673984505317317" />
            <parameter id="a_1" name="a_1" value="1.0" />
            <parameter id="a_2" name="a_2" value="0.13180742775043408" />
            <parameter id="a_3" name="a_3" value="0.7641718998234156" />
            <parameter id="k_1" name="k_1" value="0.48436266935430466" />
            <parameter id="k_2" name="k_2" value="0.6671633115387522" />
            <parameter id="n_1" name="n_1" value="2.114899245514685" />
            <parameter id="n_2" name="n_2" value="1.9667871327630084" />
          </listOfParameters>
        </kineticLaw>
      </reaction>
      <reaction id="G12_degradation" name="G12_degradation" reversible="false">
        <listOfReactants>
          <speciesReference species="G12" />
        </listOfReactants>
        <listOfProducts>
          <speciesReference species="_void_" />
        </listOfProducts>
        <kineticLaw>
          <listOfParameters>
            <parameter id="delta" name="delta" value="0.01960647439081646" />
          </listOfParameters>
        </kineticLaw>
      </reaction>
      <reaction id="G0_synthesis" name="G0_synthesis: no inputs" reversible="false">
        <listOfReactants>
          <speciesReference species="_void_" />
        </listOfReactants>
        <listOfProducts>
          <speciesReference species="G0" />
        </listOfProducts>
        <kineticLaw>
          <listOfParameters>
            <parameter id="max" name="max" value="0.02023990463201173" />
            <parameter id="deltaProtein" name="deltaProtein" value="0.022252092336593473" />
            <parameter id="maxTranslation" name="maxTranslation" value="0.022252092336593473" />
            <parameter id="a_0" name="a_0" value="1.0" />
          </listOfParameters>
        </kineticLaw>
      </reaction>
      <reaction id="G0_degradation" name="G0_degradation" reversible="false">
        <listOfReactants>
          <speciesReference species="G0" />
        </listOfReactants>
        <listOfProducts>
          <speciesReference species="_void_" />
        </listOfProducts>
        <kineticLaw>
          <listOfParameters>
            <parameter id="delta" name="delta" value="0.02023990463201173" />
          </listOfParameters>
        </kineticLaw>
      </reaction>
      <reaction id="G11_synthesis" name="G11_synthesis: ~(1) + (2)" reversible="false">
        <listOfReactants>
          <speciesReference species="_void_" />
        </listOfReactants>
        <listOfProducts>
          <speciesReference species="G11" />
        </listOfProducts>
        <listOfModifiers>
          <modifierSpeciesReference species="G0" />
          <modifierSpeciesReference species="G8" />
        </listOfModifiers>
        <kineticLaw>
          <listOfParameters>
            <parameter id="max" name="max" value="0.026130022116378448" />
            <parameter id="deltaProtein" name="deltaProtein" value="0.019953715814230392" />
            <parameter id="maxTranslation" name="maxTranslation" value="0.019953715814230392" />
            <parameter id="bindsAsComplex_1" name="bindsAsComplex_1" value="1.0" />
            <parameter id="numActivators_1" name="numActivators_1" value="1.0" />
            <parameter id="numDeactivators_1" name="numDeactivators_1" value="0.0" />
            <parameter id="bindsAsComplex_2" name="bindsAsComplex_2" value="1.0" />
            <parameter id="numActivators_2" name="numActivators_2" value="1.0" />
            <parameter id="numDeactivators_2" name="numDeactivators_2" value="0.0" />
            <parameter id="a_0" name="a_0" value="0.38471404219897887" />
            <parameter id="a_1" name="a_1" value="0.0" />
            <parameter id="a_2" name="a_2" value="1.0" />
            <parameter id="a_3" name="a_3" value="0.4754621933805029" />
            <parameter id="k_1" name="k_1" value="0.04560592307476327" />
            <parameter id="k_2" name="k_2" value="0.31528200710890814" />
            <parameter id="n_1" name="n_1" value="4.414340982000018" />
            <parameter id="n_2" name="n_2" value="1.3320724923733605" />
          </listOfParameters>
        </kineticLaw>
      </reaction>
      <reaction id="G11_degradation" name="G11_degradation" reversible="false">
        <listOfReactants>
          <speciesReference species="G11" />
        </listOfReactants>
        <listOfProducts>
          <speciesReference species="_void_" />
        </listOfProducts>
        <kineticLaw>
          <listOfParameters>
            <parameter id="delta" name="delta" value="0.026130022116378448" />
          </listOfParameters>
        </kineticLaw>
      </reaction>
      <reaction id="G10_synthesis" name="G10_synthesis: (1) + (2*3)" reversible="false">
        <listOfReactants>
          <speciesReference species="_void_" />
        </listOfReactants>
        <listOfProducts>
          <speciesReference species="G10" />
        </listOfProducts>
        <listOfModifiers>
          <modifierSpeciesReference species="G8" />
          <modifierSpeciesReference species="G0" />
          <modifierSpeciesReference species="G11" />
        </listOfModifiers>
        <kineticLaw>
          <listOfParameters>
            <parameter id="max" name="max" value="0.02275046001840734" />
            <parameter id="deltaProtein" name="deltaProtein" value="0.027706391675120644" />
            <parameter id="maxTranslation" name="maxTranslation" value="0.027706391675120644" />
            <parameter id="bindsAsComplex_1" name="bindsAsComplex_1" value="1.0" />
            <parameter id="numActivators_1" name="numActivators_1" value="1.0" />
            <parameter id="numDeactivators_1" name="numDeactivators_1" value="0.0" />
            <parameter id="bindsAsComplex_2" name="bindsAsComplex_2" value="1.0" />
            <parameter id="numActivators_2" name="numActivators_2" value="2.0" />
            <parameter id="numDeactivators_2" name="numDeactivators_2" value="0.0" />
            <parameter id="a_0" name="a_0" value="0.05134915836356032" />
            <parameter id="a_1" name="a_1" value="0.6703675278847295" />
            <parameter id="a_2" name="a_2" value="0.6537257380269729" />
            <parameter id="a_3" name="a_3" value="1.0" />
            <parameter id="k_1" name="k_1" value="0.23604376231785865" />
            <parameter id="k_2" name="k_2" value="0.05306757900398225" />
            <parameter id="k_3" name="k_3" value="0.5079119784384966" />
            <parameter id="n_1" name="n_1" value="4.854644604005525" />
            <parameter id="n_2" name="n_2" value="1.3219173381944902" />
            <parameter id="n_3" name="n_3" value="4.4352292425427615" />
          </listOfParameters>
        </kineticLaw>
      </reaction>
      <reaction id="G10_degradation" name="G10_degradation" reversible="false">
        <listOfReactants>
          <speciesReference species="G10" />
        </listOfReactants>
        <listOfProducts>
          <speciesReference species="_void_" />
        </listOfProducts>
        <kineticLaw>
          <listOfParameters>
            <parameter id="delta" name="delta" value="0.02275046001840734" />
          </listOfParameters>
        </kineticLaw>
      </reaction>
      <reaction id="G8_synthesis" name="G8_synthesis: ~(1) + ~(2)" reversible="false">
        <listOfReactants>
          <speciesReference species="_void_" />
        </listOfReactants>
        <listOfProducts>
          <speciesReference species="G8" />
        </listOfProducts>
        <listOfModifiers>
          <modifierSpeciesReference species="G12" />
          <modifierSpeciesReference species="G0" />
        </listOfModifiers>
        <kineticLaw>
          <listOfParameters>
            <parameter id="max" name="max" value="0.02393195628104466" />
            <parameter id="deltaProtein" name="deltaProtein" value="0.02341962658727905" />
            <parameter id="maxTranslation" name="maxTranslation" value="0.02341962658727905" />
            <parameter id="bindsAsComplex_1" name="bindsAsComplex_1" value="0.0" />
            <parameter id="numActivators_1" name="numActivators_1" value="1.0" />
            <parameter id="numDeactivators_1" name="numDeactivators_1" value="0.0" />
            <parameter id="bindsAsComplex_2" name="bindsAsComplex_2" value="1.0" />
            <parameter id="numActivators_2" name="numActivators_2" value="1.0" />
            <parameter id="numDeactivators_2" name="numDeactivators_2" value="0.0" />
            <parameter id="a_0" name="a_0" value="1.0" />
            <parameter id="a_1" name="a_1" value="0.6087458648429602" />
            <parameter id="a_2" name="a_2" value="0.5156604153788372" />
            <parameter id="a_3" name="a_3" value="0.12440628022179745" />
            <parameter id="k_1" name="k_1" value="0.6306981262308545" />
            <parameter id="k_2" name="k_2" value="0.31249851851025595" />
            <parameter id="n_1" name="n_1" value="3.621520830419087" />
            <parameter id="n_2" name="n_2" value="1.8816300049465318" />
          </listOfParameters>
        </kineticLaw>
      </reaction>
      <reaction id="G8_degradation" name="G8_degradation" reversible="false">
        <listOfReactants>
          <speciesReference species="G8" />
        </listOfReactants>
        <listOfProducts>
          <speciesReference species="_void_" />
        </listOfProducts>
        <kineticLaw>
          <listOfParameters>
            <parameter id="delta" name="delta" value="0.02393195628104466" />
          </listOfParameters>
        </kineticLaw>
      </reaction>
      <reaction id="G7_synthesis" name="G7_synthesis: ~(1~2) + ~(3)" reversible="false">
        <listOfReactants>
          <speciesReference species="_void_" />
        </listOfReactants>
        <listOfProducts>
          <speciesReference species="G7" />
        </listOfProducts>
        <listOfModifiers>
          <modifierSpeciesReference species="G0" />
          <modifierSpeciesReference species="G4" />
          <modifierSpeciesReference species="G5" />
        </listOfModifiers>
        <kineticLaw>
          <listOfParameters>
            <parameter id="max" name="max" value="0.03302638537355712" />
            <parameter id="deltaProtein" name="deltaProtein" value="0.023821594681993068" />
            <parameter id="maxTranslation" name="maxTranslation" value="0.023821594681993068" />
            <parameter id="bindsAsComplex_1" name="bindsAsComplex_1" value="1.0" />
            <parameter id="numActivators_1" name="numActivators_1" value="1.0" />
            <parameter id="numDeactivators_1" name="numDeactivators_1" value="1.0" />
            <parameter id="bindsAsComplex_2" name="bindsAsComplex_2" value="1.0" />
            <parameter id="numActivators_2" name="numActivators_2" value="1.0" />
            <parameter id="numDeactivators_2" name="numDeactivators_2" value="0.0" />
            <parameter id="a_0" name="a_0" value="1.0" />
            <parameter id="a_1" name="a_1" value="0.3364482151386745" />
            <parameter id="a_2" name="a_2" value="0.31845242813624575" />
            <parameter id="a_3" name="a_3" value="0.0" />
            <parameter id="k_1" name="k_1" value="0.1429733124538325" />
            <parameter id="k_2" name="k_2" value="0.3783735016337596" />
            <parameter id="k_3" name="k_3" value="0.8597985090478324" />
            <parameter id="n_1" name="n_1" value="1.3307942473667613" />
            <parameter id="n_2" name="n_2" value="1.5933813856180767" />
            <parameter id="n_3" name="n_3" value="4.915634843547201" />
          </listOfParameters>
        </kineticLaw>
      </reaction>
      <reaction id="G7_degradation" name="G7_degradation" reversible="false">
        <listOfReactants>
          <speciesReference species="G7" />
        </listOfReactants>
        <listOfProducts>
          <speciesReference species="_void_" />
        </listOfProducts>
        <kineticLaw>
          <listOfParameters>
            <parameter id="delta" name="delta" value="0.03302638537355712" />
          </listOfParameters>
        </kineticLaw>
      </reaction>
      <reaction id="G6_synthesis" name="G6_synthesis: (1) + (2~3)" reversible="false">
        <listOfReactants>
          <speciesReference species="_void_" />
        </listOfReactants>
        <listOfProducts>
          <speciesReference species="G6" />
        </listOfProducts>
        <listOfModifiers>
          <modifierSpeciesReference species="G0" />
          <modifierSpeciesReference species="G7" />
          <modifierSpeciesReference species="G4" />
        </listOfModifiers>
        <kineticLaw>
          <listOfParameters>
            <parameter id="max" name="max" value="0.028977871082932184" />
            <parameter id="deltaProtein" name="deltaProtein" value="0.022977420626541806" />
            <parameter id="maxTranslation" name="maxTranslation" value="0.022977420626541806" />
            <parameter id="bindsAsComplex_1" name="bindsAsComplex_1" value="0.0" />
            <parameter id="numActivators_1" name="numActivators_1" value="1.0" />
            <parameter id="numDeactivators_1" name="numDeactivators_1" value="0.0" />
            <parameter id="bindsAsComplex_2" name="bindsAsComplex_2" value="1.0" />
            <parameter id="numActivators_2" name="numActivators_2" value="1.0" />
            <parameter id="numDeactivators_2" name="numDeactivators_2" value="1.0" />
            <parameter id="a_0" name="a_0" value="0.04955866534034052" />
            <parameter id="a_1" name="a_1" value="0.524624092647319" />
            <parameter id="a_2" name="a_2" value="0.6441567572016664" />
            <parameter id="a_3" name="a_3" value="1.0" />
            <parameter id="k_1" name="k_1" value="0.49410091019934044" />
            <parameter id="k_2" name="k_2" value="0.5595775679964572" />
            <parameter id="k_3" name="k_3" value="0.7788413827423938" />
            <parameter id="n_1" name="n_1" value="5.703139707514175" />
            <parameter id="n_2" name="n_2" value="2.407096568530095" />
            <parameter id="n_3" name="n_3" value="1.940792159105855" />
          </listOfParameters>
        </kineticLaw>
      </reaction>
      <reaction id="G6_degradation" name="G6_degradation" reversible="false">
        <listOfReactants>
          <speciesReference species="G6" />
        </listOfReactants>
        <listOfProducts>
          <speciesReference species="_void_" />
        </listOfProducts>
        <kineticLaw>
          <listOfParameters>
            <parameter id="delta" name="delta" value="0.028977871082932184" />
          </listOfParameters>
        </kineticLaw>
      </reaction>
      <reaction id="G5_synthesis" name="G5_synthesis: ~(1) + ~(2) + ~(3)" reversible="false">
        <listOfReactants>
          <speciesReference species="_void_" />
        </listOfReactants>
        <listOfProducts>
          <speciesReference species="G5" />
        </listOfProducts>
        <listOfModifiers>
          <modifierSpeciesReference species="G4" />
          <modifierSpeciesReference species="G6" />
          <modifierSpeciesReference species="G0" />
        </listOfModifiers>
        <kineticLaw>
          <listOfParameters>
            <parameter id="max" name="max" value="0.02789110344368605" />
            <parameter id="deltaProtein" name="deltaProtein" value="0.018629063390303787" />
            <parameter id="maxTranslation" name="maxTranslation" value="0.018629063390303787" />
            <parameter id="bindsAsComplex_1" name="bindsAsComplex_1" value="1.0" />
            <parameter id="numActivators_1" name="numActivators_1" value="1.0" />
            <parameter id="numDeactivators_1" name="numDeactivators_1" value="0.0" />
            <parameter id="bindsAsComplex_2" name="bindsAsComplex_2" value="1.0" />
            <parameter id="numActivators_2" name="numActivators_2" value="1.0" />
            <parameter id="numDeactivators_2" name="numDeactivators_2" value="0.0" />
            <parameter id="bindsAsComplex_3" name="bindsAsComplex_3" value="0.0" />
            <parameter id="numActivators_3" name="numActivators_3" value="1.0" />
            <parameter id="numDeactivators_3" name="numDeactivators_3" value="0.0" />
            <parameter id="a_0" name="a_0" value="1.0" />
            <parameter id="a_1" name="a_1" value="0.31877582615265565" />
            <parameter id="a_2" name="a_2" value="0.32252600122435393" />
            <parameter id="a_3" name="a_3" value="0.0" />
            <parameter id="a_4" name="a_4" value="0.29347179725735617" />
            <parameter id="a_5" name="a_5" value="0.0" />
            <parameter id="a_6" name="a_6" value="0.0" />
            <parameter id="a_7" name="a_7" value="0.0" />
            <parameter id="k_1" name="k_1" value="0.20974574882071467" />
            <parameter id="k_2" name="k_2" value="0.9411532825417817" />
            <parameter id="k_3" name="k_3" value="0.2452937918365933" />
            <parameter id="n_1" name="n_1" value="3.1045168200874547" />
            <parameter id="n_2" name="n_2" value="3.4040393156109077" />
            <parameter id="n_3" name="n_3" value="5.258266020064665" />
          </listOfParameters>
        </kineticLaw>
      </reaction>
      <reaction id="G5_degradation" name="G5_degradation" reversible="false">
        <listOfReactants>
          <speciesReference species="G5" />
        </listOfReactants>
        <listOfProducts>
          <speciesReference species="_void_" />
        </listOfProducts>
        <kineticLaw>
          <listOfParameters>
            <parameter id="delta" name="delta" value="0.02789110344368605" />
          </listOfParameters>
        </kineticLaw>
      </reaction>
    </listOfReactions>
  </model>
</sbml>
